setup.cfg
setup.py
baytech/__init__.py
baytech/rpc3nc.py
baytech.egg-info/PKG-INFO
baytech.egg-info/SOURCES.txt
baytech.egg-info/dependency_links.txt
baytech.egg-info/pbr.json
baytech.egg-info/top_level.txt