Metadata-Version: 1.1
Name: baytech
Version: 0.2
Summary: Control Baytech products via telnet.
Home-page: https://github.com/arnaudcoquelet/python-baytech/
Author: arnaudcoquelet
Author-email: arcoquel@gmail.com
License: MIT
Download-URL: https://github.com/arnaudcoquelet/python-baytech/tarball/0.2
Platform: UNKNOWN
Classifier: License :: OSI Approved :: MIT License
Classifier: Operating System :: OS Independent
Classifier: Programming Language :: Python :: 3
